odoo/addons/fs_base_multi_media/README.rst
odoo/addons/fs_base_multi_media/__init__.py
odoo/addons/fs_base_multi_media/__manifest__.py
odoo/addons/fs_base_multi_media/i18n/es.po
odoo/addons/fs_base_multi_media/i18n/fs_base_multi_media.pot
odoo/addons/fs_base_multi_media/i18n/it.po
odoo/addons/fs_base_multi_media/models/__init__.py
odoo/addons/fs_base_multi_media/models/fs_media.py
odoo/addons/fs_base_multi_media/models/fs_media_relation_mixin.py
odoo/addons/fs_base_multi_media/models/fs_media_type.py
odoo/addons/fs_base_multi_media/readme/CONTRIBUTORS.md
odoo/addons/fs_base_multi_media/readme/DESCRIPTION.md
odoo/addons/fs_base_multi_media/readme/ROADMAP.md
odoo/addons/fs_base_multi_media/readme/USAGE.md
odoo/addons/fs_base_multi_media/security/fs_media.xml
odoo/addons/fs_base_multi_media/security/fs_media_type.xml
odoo/addons/fs_base_multi_media/security/res_groups.xml
odoo/addons/fs_base_multi_media/static/description/icon.png
odoo/addons/fs_base_multi_media/static/description/index.html
odoo/addons/fs_base_multi_media/views/fs_media.xml
odoo/addons/fs_base_multi_media/views/fs_media_relation_mixin.xml
odoo/addons/fs_base_multi_media/views/fs_media_type.xml
odoo_addon_fs_base_multi_media-17.0.1.0.0.3.dist-info/METADATA
odoo_addon_fs_base_multi_media-17.0.1.0.0.3.dist-info/WHEEL
odoo_addon_fs_base_multi_media-17.0.1.0.0.3.dist-info/top_level.txt
odoo_addon_fs_base_multi_media-17.0.1.0.0.3.dist-info/RECORD
