Metadata-Version: 2.1
Name: odoo-addon-fs_base_multi_media
Version: 17.0.1.0.0.3
Requires-Python: >=3.10
Requires-Dist: odoo-addon-fs_file>=17.0dev,<17.1dev
Requires-Dist: odoo>=17.0a,<17.1dev
Summary: Give the possibility to store media data in external filesystem from odoo
Home-page: https://github.com/OCA/storage
License: AGPL-3
Author: ACSONE SA/NV,Akretion,Odoo Community Association (OCA)
Author-email: support@odoo-community.org
Classifier: Programming Language :: Python
Classifier: Framework :: Odoo
Classifier: Framework :: Odoo :: 17.0
Classifier: License :: OSI Approved :: GNU Affero General Public License v3
Classifier: Development Status :: 3 - Alpha
